{"capitalizedSentences": [{"tokens": ["Apple", "Removes", "Fitbit", "Devices", "Online", ",", "but", "Not", "from", "Stores"], "pos": ["name", "tv", "name_oov", "C*_oov", "C*", "punct", "d", "d", "p", "n"], "no": 0}], "otherSentences": [{"tokens": ["The", "Fitbit", "activity", "tracker", "is", "no", "longer", "available", "via", "Apple", "'s", "online", "store", "."], "pos": ["det", "name", "n", "n", "tv", "d", "C*_oov", "adj", "p", "name", "tv", "adj", "n", "punct"], "no": 1}, {"tokens": ["A", "dispute", "between", "the", "two", "companies", "may", "be", "behind", "the", "move", "."], "pos": ["det", "n", "p", "det", "q", "n", "w", "v", "p", "det", "n", "punct"], "no": 2}, {"tokens": ["Jason", "Cipriani", "-", "CNET"], "pos": ["name", "C*_oov", "C*_oov", "C*_oov"], "no": 3}, {"tokens": ["Apple", "is", "no", "longer", "selling", "Fitbit", "fitness", "-", "tracking", "bands", "on", "its", "website", ",", "but", "they", "can", "still", "be", "found", "in", "the", "company", "'s", "retail", "stores", ",", "at", "least", "for", "now", "."], "pos": ["name", "tv", "d", "C*_oov", "ving", "name", "n", null, "ving", "n", "p", "det", "n", "punct", "p", "pro", "w", "d", "v", "ven", "csn", "det", "n", "tv", "n", "n", "punct", "d", "C*_oov", "p", "d", "punct"], "no": 4}, {"tokens": ["Until", "late", "last", "week", ",", "Apple", "'s", "online", "store", "offered", "both", "the", "Fitbit", "One", "and", "the", "Fitbit", "Flex", ",", "along", "with", "other", "third", "-", "party", "activity", "bands", "."], "pos": ["csn", "ngTime", "C*_oov", "C*_oov", "punct", "name", "tv", "adj", "n", "tv", "q", "det", "name_oov", "C*", null, "det", "name_oov", "C*", "punct", "p", "C*_oov", "adj", "ordinal", null, "n", "n", "n", "punct"], "no": 5}, {"tokens": ["But", "now", "a", "search", "for", "Fitbit", "at", "Apple", "'s", "website", "comes", "up", "empty", "."], "pos": ["d", "d", "det", "n", "p", "name", "p", "name", "tv", "n", "tv", "d", "adj", "punct"], "no": 6}, {"tokens": ["Apple", "removed", "Fitbit", "products", "from", "its", "website", "on", "Friday", ",", "9", "to", "5", "Mac", "reported", "."], "pos": ["name", "tv", "name", "n", "p", "det", "n", "p", "ngTime", "punct", "q", "p", "q", "name", "tv", "punct"], "no": 7}, {"tokens": ["But", "the", "Fitbit", "One", "and", "Fitbit", "Flex", "both", "remain", "available", "at", "Apple", "retail", "stores", "around", "the", "country", ",", "AppleInsider", "reported", "Monday", "."], "pos": ["p", "det", "name_oov", "C*", null, "name_oov", "C*", "q", "v", "adj", "p", "name", "n", "n", "p", "det", "n", "punct", "name", "tv", "ngTime", "punct"], "no": 8}, {"tokens": ["How", "long", "they", "will", "be", "available", "remains", "a", "question", "."], "pos": [null, "d", "pro", "w", "v", "adj", "tv", "det", "n", "punct"], "no": 9}, {"tokens": ["Apple", "store", "employees", "asked", "by", "AppleInsider", "about", "the", "status", "of", "the", "Fitbit", "products", "were", "unable", "to", "predict", "."], "pos": ["name", "n", "n", "tv", "p", "name", "p", "det", "n", "p", "det", "name", "n", "tv", "adj", "p", "v", "punct"], "no": 10}, {"tokens": ["Apple", "had", "already", "removed", "Fitbit", "from", "the", "Apps", "for", "Health", "section", "of", "the", "Apple", "App", "Store", "late", "last", "month", "."], "pos": ["name", "tv", "d", "ven", "name", "p", "det", "name_oov", "p", "name", "n", "p", "det", "name", "C*_oov", "C*", "ngTime", "C*_oov", "C*_oov", "punct"], "no": 11}, {"tokens": ["An", "Apple", "representative", "declined", "CNET", "'s", "request", "for", "comment", "."], "pos": ["det", "name", "n", "tv", "name", "tv", "n", "p", "n", "punct"], "no": 12}, {"tokens": ["Fitbit", "did", "not", "immediately", "respond", "to", "CNET", "'s", "request", "for", "comment", "."], "pos": ["name", "tv", "d", "d", "v", "p", "name", "tv", "n", "p", "n", "punct"], "no": 13}, {"tokens": ["So", "why", "are", "the", "devices", "no", "longer", "available", "online", "?"], "pos": ["d", null, "tv", "det", "n", "d", "C*_oov", "adj", "adj", "punct"], "no": 14}, {"tokens": ["The", "answer", "most", "likely", "lies", "in", "Fitbit", "'s", "incompatibility", "with", "Apple", "'s", "HealthKit", "developers", "tool", "released", "in", "September", "."], "pos": ["det", "n", "d", "adj", "n", "csn", "name", "tv", "n", "csn", "name", "tv", "name_oov", "n", "n", "ven", "csn", "ngTime", "punct"], "no": 15}, {"tokens": ["Late", "last", "month", ",", "Fitbit", "released", "a", "statement", "about", "the", "HealthKit", "health", "-", "data", "platform", ":"], "pos": ["ngTime", "C*_oov", "C*_oov", "punct", "name", "tv", "det", "n", "p", "det", "name_oov", "n", null, "n", "n", "punct"], "no": 16}, {"tokens": ["For", "the", "past", "few", "years", ",", "we", "'ve", "been", "the", "leader", "in", "developing", "direct", "partnerships", "through", "our", "open", "API", ",", "the", "company", "said", "."], "pos": ["p", "det", "adj", "adj", "n", "punct", "pro", "tv", "ven", "det", "n", "csn", "ving", "adj", "n", "p", "det", "adj", "name_oov", "punct", "det", "n", "tv", "punct"], "no": 17}, {"tokens": ["HealthKit", "is", "really", "interesting", "to", "us", ",", "Fitbit", "said", ",", "but", "its", "lack", "of", "compatibility", "with", "Google", "'s", "Android", "mobile", "OS", "led", "to", "a", "decision", "to", "not", "immediately", "integrate", "with", "HealthKit", "."], "pos": ["name_oov", "tv", "d", "adj", "p", "pro", "punct", "name", "tv", "punct", "p", "det", "n", "p", "n", "csn", "name", "tv", "n", "adj", "name_oov", "tv", "p", "det", "n", "p", "d", "d", "v", "csn", "name_oov", "punct"], "no": 18}, {"tokens": ["Last", "week", ",", "Fitbit", "reiterated", "its", "position", "on", "its", "forum", ",", "according", "to", "9", "to", "5", "Mac", ":"], "pos": ["ngTime", "C*_oov", "punct", "name", "tv", "det", "n", "p", "det", "n", "punct", "p", "C*_oov", "q", "p", "q", "name", "punct"], "no": 19}, {"tokens": ["We", "do", "not", "currently", "have", "plans", "to", "integrate", "with", "HealthKit", ".", ".", ".", ".", "It", "is", "an", "interesting", "new", "platform", "and", "we", "will", "watch", "as", "it", "matures", ",", "looking", "for", "opportunities", "to", "improve", "the", "Fitbit", "experience", "."], "pos": ["pro", "tv", "d", "d", "v", "n", "p", "v", "csn", "name_oov", "punct", "punct", "punct", "punct", "name", "tv", "det", "adj", "adj", "n", null, "pro", "w", "v", "csn", "pro", "tv", "punct", "ving", "p", "n", "p", "v", "det", "name", "n", "punct"], "no": 20}, {"tokens": ["At", "the", "moment", ",", "we", "'re", "working", "on", "other", "exciting", "projects", "that", "we", "think", "will", "be", "valuable", "to", "users", "."], "pos": ["p", "det", "n", "punct", "pro", "tv", "ving", "p", "adj", "ving", "n", "d", "pro", "tv", "w", "v", "adj", "p", "n", "punct"], "no": 21}, {"tokens": ["Fitbit", "did", "raise", "the", "possibility", "of", "altering", "its", "plans", "if", "it", "receives", "enough", "demand", "from", "Apple", "customers", ",", "though", "."], "pos": ["name", "tv", "v", "det", "n", "p", "ving", "det", "n", "csn", "pro", "tv", "adj", "n", "p", "name", "n", "punct", "csn", "punct"], "no": 23}, {"tokens": ["The", "question", "we", "want", "you", "to", "keep", "in", "mind", "when", "providing", "feedback", "is", ":"], "pos": ["det", "n", "pro", "tv", "pro", "p", "v", "csn", "n", "csn", "ving", "n", "tv", "punct"], "no": 24}, {"tokens": ["What", "do", "you", "imagine", "a", "HealthKit", "integration", "would", "entail", "and", "what", "do", "you", "expect", "to", "get", "out", "of", "it", "?"], "pos": [null, "tv", "pro", "v", "det", "name_oov", "n", "w", "v", null, null, "tv", "pro", "tv", "p", "v", "p", "C*_oov", "pro", "punct"], "no": 25}, {"tokens": ["Fitbit", "asked", "on", "its", "forum", "."], "pos": ["name", "tv", "p", "det", "n", "punct"], "no": 26}, {"tokens": ["Your", "voices", "are", "being", "heard", "."], "pos": ["det", "n", "tv", "ving", "ven", "punct"], "no": 27}, {"tokens": ["We", "'re", "actively", "reviewing", "your", "responses", "and", "providing", "feedback", "to", "our", "product", "development", "team", "."], "pos": ["pro", "tv", "d", "ving", "det", "n", null, "ving", "n", "p", "det", "n", "n", "n", "punct"], "no": 28}]}
